LICENSE
README.md
setup.cfg
setup.py
objseg/__init__.py
objseg/basic_preprocessing.py
objseg/blocked_gibbs.py
objseg/blocked_gibbs_functions.py
objseg/box.py
objseg/cli.py
objseg/hybrid_gibbs.py
objseg/object_center_position_search.py
objseg/post_process.py
objseg/priors.py
objseg/results_analyses.py
objseg/rtree_functions.py
objseg/rtree_functions_jitclass.py
objseg/runseg.py
objseg/shapes.py
objseg/single_site_gibbs.py
objseg/step1_functions.py
objseg/step1_posterior.py
objseg/step2_functions.py
objseg/step2_shapes_adapMH.py
objseg/step3_update.py
objseg/variational_mf.py
objseg.egg-info/PKG-INFO
objseg.egg-info/SOURCES.txt
objseg.egg-info/dependency_links.txt
objseg.egg-info/entry_points.txt
objseg.egg-info/not-zip-safe
objseg.egg-info/requires.txt
objseg.egg-info/top_level.txt