Metadata-Version: 2.1
Name: objseg
Version: 0.2.2
Summary: A cell segmentation pipeline
Home-page: https://github.com/tsuijenk/BLMPP
Author: Jenkin Tsui
Author-email: jenkin.tsui@aya.yale.edu
License: GPL v3
Platform: UNKNOWN
Classifier: Programming Language :: Python :: 3
Classifier: Operating System :: OS Independent
Requires-Python: >=3.7
License-File: LICENSE
